zulu/__init__.py
zulu/aws.py
zulu/main.py
zulu/secrets_tool.py
zulu_cli-0.2.7.dist-info/LICENSE
zulu_cli-0.2.7.dist-info/METADATA
zulu_cli-0.2.7.dist-info/WHEEL
zulu_cli-0.2.7.dist-info/entry_points.txt
zulu_cli-0.2.7.dist-info/top_level.txt
zulu_cli-0.2.7.dist-info/RECORD
